parallel_tokenizer/__init__.py
parallel_tokenizer/logger.py
parallel_tokenizer/parallel_tokenizer.py
parallel_tokenizer/sp_tokenizer.py
parallel_tokenizer/utils.py
ParallelTokenizer-0.1.0.dist-info/LICENSE
ParallelTokenizer-0.1.0.dist-info/METADATA
ParallelTokenizer-0.1.0.dist-info/WHEEL
ParallelTokenizer-0.1.0.dist-info/top_level.txt
ParallelTokenizer-0.1.0.dist-info/RECORD
