Metadata-Version: 2.1
Name: ParallelTokenizer
Version: 0.1.0
Summary: a tool that uses a parallel approach to tokenizer to achieve superior acceleration
Classifier: Programming Language :: Python :: 3.8
Classifier: Programming Language :: Python :: 3.9
Classifier: Programming Language :: Python :: 3.10
Classifier: Programming Language :: Python :: 3.11
Classifier: Intended Audience :: Developers
Classifier: Intended Audience :: Education
Classifier: Intended Audience :: Science/Research
License-File: LICENSE
